vspagent/__init__.py
vspagent/agent.py
vspagent/cli.py
vspagent-2.2.0.dist-info/licenses/LICENSE
vspagent-2.2.0.dist-info/METADATA
vspagent-2.2.0.dist-info/WHEEL
vspagent-2.2.0.dist-info/entry_points.txt
vspagent-2.2.0.dist-info/top_level.txt
vspagent-2.2.0.dist-info/RECORD
