Metadata-Version: 2.4
Name: vspagent
Version: 2.2.0
Summary: AI-powered chat agent about Vishnu Suresh Perumbavoor. Powered by Qwen2.5-0.5B.
Home-page: https://github.com/vishnusureshperumbavoor/vsp_bot
Author: Vishnu Suresh Perumbavoor
Author-email: vishnusureshperumbavoor@gmail.com
Project-URL: Bug Tracker, https://github.com/vishnusureshperumbavoor/vsp_bot/issues
Project-URL: LinkedIn, https://www.linkedin.com/in/vishnu-suresh-perumbavoor/
Project-URL: GitHub, https://github.com/vishnusureshperumbavoor
Keywords: ai agent chatbot qwen llm vsp transformers
Classifier: Development Status :: 4 - Beta
Classifier: Intended Audience :: Developers
Classifier: Topic :: Scientific/Engineering :: Artificial Intelligence
Classifier: License :: OSI Approved :: MIT License
Classifier: Programming Language :: Python :: 3
Classifier: Programming Language :: Python :: 3.8
Classifier: Programming Language :: Python :: 3.9
Classifier: Programming Language :: Python :: 3.10
Classifier: Programming Language :: Python :: 3.11
Requires-Python: >=3.8
License-File: LICENSE
Requires-Dist: transformers>=4.30.0
Requires-Dist: torch>=2.0.0
Dynamic: author
Dynamic: author-email
Dynamic: classifier
Dynamic: description
Dynamic: description-content-type
Dynamic: home-page
Dynamic: keywords
Dynamic: license-file
Dynamic: project-url
Dynamic: requires-dist
Dynamic: requires-python
Dynamic: summary
